latpypack/__init__.py
latpypack/common.py
latpypack/latpypack.py
latpypack-0.0.1.dist-info/LICENSE
latpypack-0.0.1.dist-info/METADATA
latpypack-0.0.1.dist-info/WHEEL
latpypack-0.0.1.dist-info/entry_points.txt
latpypack-0.0.1.dist-info/top_level.txt
latpypack-0.0.1.dist-info/RECORD
